aury/__init__.py
aury/agents/__init__.py
aury/agents/plugin.py
aury/agents/a2a/__init__.py
aury/agents/backends/__init__.py
aury/agents/backends/sandbox.py
aury/agents/backends/shell.py
aury/agents/backends/code/__init__.py
aury/agents/backends/file/__init__.py
aury/agents/backends/file/local.py
aury/agents/backends/file/types.py
aury/agents/backends/shell/__init__.py
aury/agents/backends/shell/local.py
aury/agents/backends/shell/types.py
aury/agents/backends/snapshot/__init__.py
aury/agents/backends/snapshot/git.py
aury/agents/backends/snapshot/hybrid.py
aury/agents/backends/snapshot/memory.py
aury/agents/backends/snapshot/types.py
aury/agents/backends/state/__init__.py
aury/agents/backends/state/composite.py
aury/agents/backends/state/file.py
aury/agents/backends/state/memory.py
aury/agents/backends/state/sqlite.py
aury/agents/backends/state/types.py
aury/agents/backends/subagent/__init__.py
aury/agents/cli/__init__.py
aury/agents/cli/chat.py
aury/agents/cli/config.py
aury/agents/cli/extensions.py
aury/agents/cli/main.py
aury/agents/cli/session.py
aury/agents/cli/workflow.py
aury/agents/context_providers/__init__.py
aury/agents/context_providers/artifact.py
aury/agents/context_providers/base.py
aury/agents/context_providers/memory.py
aury/agents/context_providers/message.py
aury/agents/context_providers/skill.py
aury/agents/context_providers/subagent.py
aury/agents/context_providers/tool.py
aury/agents/core/__init__.py
aury/agents/core/base.py
aury/agents/core/context.py
aury/agents/core/context_builder.py
aury/agents/core/factory.py
aury/agents/core/isolator.py
aury/agents/core/logging.py
aury/agents/core/parallel.py
aury/agents/core/runner.py
aury/agents/core/state.py
aury/agents/core/bus/__init__.py
aury/agents/core/bus/bus.py
aury/agents/core/services/__init__.py
aury/agents/core/services/file_session.py
aury/agents/core/services/message.py
aury/agents/core/services/session.py
aury/agents/core/types/__init__.py
aury/agents/core/types/action.py
aury_agents-0.0.3.dist-info/METADATA
aury_agents-0.0.3.dist-info/WHEEL
aury_agents-0.0.3.dist-info/entry_points.txt
aury_agents-0.0.3.dist-info/RECORD
