Metadata-Version: 2.4
Name: aury-agents
Version: 0.0.3
Summary: Aury Agent Framework - React Agent and Workflow orchestration
Author: Aury Team
License: MIT
Keywords: agent,llm,react,workflow
Classifier: Development Status :: 3 - Alpha
Classifier: Intended Audience :: Developers
Classifier: License :: OSI Approved :: MIT License
Classifier: Programming Language :: Python :: 3
Classifier: Programming Language :: Python :: 3.13
Requires-Python: >=3.13
Requires-Dist: aiofiles>=23.0.0
Requires-Dist: aury-ai-model[all]
Requires-Dist: pydantic>=2.0.0
Requires-Dist: python-dotenv>=1.0.0
Requires-Dist: pyyaml>=6.0.0
Requires-Dist: rich>=13.0.0
Requires-Dist: typer>=0.9.0
Provides-Extra: all
Requires-Dist: anthropic>=0.20.0; extra == 'all'
Requires-Dist: openai>=1.0.0; extra == 'all'
Provides-Extra: anthropic
Requires-Dist: anthropic>=0.20.0; extra == 'anthropic'
Provides-Extra: memory
Requires-Dist: chromadb>=0.4.0; extra == 'memory'
Provides-Extra: openai
Requires-Dist: openai>=1.0.0; extra == 'openai'
